<?xml version="1.0" encoding="UTF-8"?>
<gresources>
  <gresource prefix="/dev/bragefuglseth/Keypunch">
    <file preprocess="xml-stripblanks">window.ui</file>
    <file preprocess="xml-stripblanks">text_view.ui</file>
    <file preprocess="xml-stripblanks">gtk/help-overlay.ui</file>
    <file>style.css</file>
  </gresource>

  <gresource prefix="/dev/bragefuglseth/Keypunch/icons/scalable/actions/">
    <file alias="stop-symbolic.svg" preprocess="xml-stripblanks">ui/icons/stop-symbolic.svg</file>
  </gresource>
</gresources>
